Local/ALU.v
module ALU(A, B, Cin, FS, Y, N, C, V, Z);
	parameter n = 32;
	input [n-1:0] A, B;
	input Cin;
	input [3:0] FS;

	output reg [n-1:0] Y;
	output reg N, C, V, Z;

	wire [n-1:0] Yt;
	wire Cout;
	wire mode;
	wire cin;

	wire [n-1:0] tmpA, tmpB;
	assign tmpA[15:0] = A[15:0];
	assign tmpB[15:0] = B[15:0];
	assign tmpA[n-1:16] = {n-16{A[15]}};
	assign tmpB[n-1:16] = {n-16{B[15]}};

	AdderSubstractor AddSub(A, B, cin, mode, Cout, Yt);

	assign cin = (FS==4'b0101) ? Cin : 1'b0 ;
	assign mode = (FS==4'b0110||FS==4'b0111) ? 1'b1 : 1'b0 ;

	always@(*)begin
		N = Y[n-1];
		Z = (Y==32'd0)?1'b1:1'b0;
		case(FS)
			4'b0000, 4'b0010,
			4'b1100, 4'b1101, 4'b1110, 4'b1111:begin
				N = 1'b0;
				Z = 1'b0;
			end
		endcase
	end

	always@(*)begin
		C = 1'b0;
		V = 1'b0;
		case(FS)
			4'b0001:begin
				C = A[n-1];
				V = A[n-1] ^ A[n-2];					
			end
			4'b0100, 4'b0101, 
			4'b0110, 4'b0111:begin
				C = Cout;
				V =
				  (	( (A[n-1]==1'b1) & (B[n-1]==1'b0) & (mode==1'b1) & (Y[n-1]==1'b0) ) |
					( (A[n-1]==1'b0) & (B[n-1]==1'b1) & (mode==1'b1) & (Y[n-1]==1'b1) ) |
					( (A[n-1]==1'b1) & (B[n-1]==1'b1) & (mode==1'b0) & (Y[n-1]==1'b0) ) |
					( (A[n-1]==1'b0) & (B[n-1]==1'b0) & (mode==1'b0) & (Y[n-1]==1'b1) ) ) ?
				  		1'b1 : 1'b0 ;
			end
		endcase
	end

	always@(*)begin
		case(FS)
			// logic left shift
			4'b0000:begin
				Y[n-1:1] = A[n-2:0];
				Y[0] = 1'b0;
			end
			// arithmetic left shift 
			4'b0001:begin
				Y[n-1:1] = A[n-2:0];
				Y[0] = 1'b0;

			end
			// srl
			4'b0010:begin
				Y[n-2:0] = A[n-1:1];
				Y[n-1] = 1'b0;
			end
			// sra
			4'b0011:begin
				Y[n-2:0] = A[n-1:1];
				Y[n-1] = (Y[n-2]==1'b1)?1'b1:1'b0;
			end
			// add
			4'b0100:begin
				Y = Yt;
			end
			// add with carry
			4'b0101:begin
				Y = Yt;
			end
			// sub
			4'b0110:begin
				Y = Yt;
			end
			// abs
			4'b0111:begin
				Y = (Yt[n-1]==1'b1) ? (Yt ^ {n{1'b1}}) + 1 : Yt ;
			end
			// multi
			4'b1000:begin
				Y = tmpA * tmpB;
			end
			// zero
			4'b1001:begin
				Y = 32'd0;
			end
			// output A
			4'b1010:begin
				Y = A;
			end
			// output B
			4'b1011:begin
				Y = B;
			end
			// and
			4'b1100:begin
				Y = A & B;
			end
			// or
			4'b1101:begin
				Y = A | B;
			end
			// xor
			4'b1110:begin
				Y = A ^ B;
			end
			// not
			4'b1111:begin
				Y = ~A;
			end
		endcase
	end

endmodule

module HalfAdder(A, B, Cin, Cout, Y);
	input A, B, Cin;
	output Cout, Y;

	wire o1, o2, o3;

	xor xor1(Y, A, B, Cin);
	and and1(o1, A, B);
	and and2(o2, A, Cin);
	and and3(o3, B, Cin);
	or or1(Cout, o1, o2, o3);
endmodule

module AdderSubstractor(A, B, Cin, mode, Cout, Y);
	parameter n = 32;
	input [n-1:0] A, B;
	input mode, Cin;
	output Cout;
	output [n-1:0] Y;

	wire Cout;
	wire [n-1:0] Bx;
	wire [n:0] C;

	assign C[0] = mode | Cin;
	assign Bx = B ^ {n{mode}};
	assign Y = A ^ Bx ^ C[n-1:0];
	assign C[n:1] = A & Bx | A & C[n-1:0] | Bx & C[n-1:0];
	assign Cout = C[n];
endmodule

Local/VIP_tb.v
`define SDFFILE   "./VIP.sdf"
`define End_CYCLE  1000000000

`define info  "./info.dat"   

module IP_tb;
	//Clock period
	parameter cyc = 24;
	
	parameter dataWidth=32;
	parameter memWidth=10;

	// #pattern
	parameter PAT = 1026;

	reg [dataWidth-1:0]dataROM[0:PAT-1];
	reg [memWidth-1:0]maxSize;

	reg clk, rst_n, Start;
	reg [dataWidth-1:0]Data;
	wire Finish, En;
	wire [dataWidth-1:0]Result;
	wire [memWidth-1:0]Addr;

	//VIP module
	VIP vip( 
		.clk(clk),
		.rst_n(rst_n), 
		.Start(Start), 
		.Data(Data),
		.Addr(Addr),
		.Result(Result),
		.Finish(Finish),
		.En(En)
	);
	
	always #(cyc/2) clk = ~clk;
	
	initial begin
		`ifdef SDF
			$sdf_annotate(`SDFFILE, vip);
			$dumpfile("VIP_syn.vcd");
		`else
			$dumpfile("VIP.vcd");
		`endif
		$dumpvars;
	end

	
	initial begin
		
		//Init ROM
		$readmemb ("info.dat", dataROM);

		maxSize = 10'd1023;
	
		rst_n = 1'b1;
		clk = 1'b0;
		Start = 1'b0;
		Data = 'hz;

		@(negedge clk)  rst_n = 1'b0; 
		#(cyc*2);    rst_n = 1'b1; 
		
		@(negedge clk)  Start = 1'b1;
		while (Finish == 0) begin             
			if(En && Addr <= maxSize) begin
				Data = dataROM[Addr];  
				
			end else begin
				Data = 'hz;  
		
			end                    
			@(negedge clk);  

		end 
		$display(" ");
		if($signed(Result) == $signed(dataROM[1024]))begin
			$display("Congratulations !! :)");
			$display(" ");
			$finish;

		end

		$display("Wrong Answer !! :(");
	    $display("Result = %d, Answer = %d", $signed(Result), $signed(dataROM[1024]));
		$display(" ");
		$finish;
	end
	
	initial  begin
		#`End_CYCLE ;
		$display("-----------------------------------------------------\n");
		$display("Error!!! Somethings' wrong with your code ...!\n");
		$display("-------------------------FAIL------------------------\n");
		$display("-----------------------------------------------------\n");
		$finish;
	end

endmodule

Local/VIP.v
module VIP(clk, rst_n, Start, Data, Addr, Result, Finish, En);

	parameter memWidth = 10;
	parameter dataWidth = 32;

	input clk, rst_n, Start;
	input [dataWidth-1:0]Data;

	output reg [dataWidth-1:0]Result;
	output reg [memWidth-1:0]Addr;
	output reg Finish, En;

	// d flip-flop
	reg  [dataWidth-1:0] nextRomX, nextSum, nextAmt;
	reg  [dataWidth-1:0] romX, sum, prevResult, amt;	// wire
	reg  [memWidth-1:0]  prevAddr;	// wire
	reg  [1:0] state;	// wire
	reg  [1:0] nextState;
	/*DFF #(3) 		status(clk, nextState, 		 state);
	DFF #(dataWidth)    r0(clk,  nextRomX, 		  romX);
	DFF #(dataWidth)   Acc(clk,    Result,  prevResult);
	DFF #(memWidth) memRAM(clk, 	 Addr, 	  prevAddr);
	DFF #(dataWidth)  temp(clk,   nextSum, 		   sum);
	DFF #(dataWidth)  left(clk,   nextAmt, 		   amt);*/
	always@(negedge clk)begin	// a big combined D-flipflop
		state = nextState ;
		romX  =  nextRomX ;
		sum   =   nextSum ;
		amt   =   nextAmt ;
		prevAddr   = Addr ;
		prevResult = Result ;
	end

	// states
	parameter IDLE = 2'b00;
	parameter X_0  = 2'b01;
	parameter MUL  = 2'b10;
	parameter ADD  = 2'b11;

	// ALU
	wire [dataWidth-1:0] A, B, Y;
	wire [3:0] FS;
	wire Cin, N, C, V, Z;
	assign  A = (state == MUL) ? romX : sum ;
	assign  B = (state == MUL) ? Data : prevResult ;
	assign FS = (state == MUL) ? 4'b1000 : 4'b0100 ;
	ALU AddMul(A, B, Cin, FS, Y, N, C, V, Z);

	// finite state machine
	always@(negedge rst_n)begin
		//if (!rst_n) begin	// initialize
			nextState = IDLE;
			En = 1;
			Finish = 0;
			Result = 0;
		//end
	end
	
	always@(posedge clk)begin
		case(state)
			IDLE:begin
				Addr = 10'd1023;
				if (Start)begin
					nextAmt = Data ;
					Addr = 0;
					nextState = X_0;
				end else begin
					nextState = IDLE;
					end
				end
			X_0:begin
				nextRomX = Data;
				Addr = prevAddr + 1;
				nextAmt = amt - 1;
				nextState = MUL;
				end
			MUL:begin
				nextAmt = amt - 1;
				Addr = prevAddr + 1;
				nextSum = Y;	// ALU
				nextState = ADD;
				end
			ADD:begin
				if (amt == 0)begin
					Finish = 1;
				end else begin
					nextRomX = Data;
					Addr = prevAddr + 1 ;
					nextAmt = amt - 1;
					nextState = MUL;
				end
				Result = Y;
				end
		endcase
	end
	
endmodule

module DFF(clk, in, out);
	parameter n = 1;
	input clk;
	input [n-1:0] in ;
	output reg [n-1:0] out ;
	
	always @(negedge clk)
		out = in ;
endmodule

Local/VIP.vcd
$date
	Sun Apr 16 04:06:00 2017
$end
$version
	Icarus Verilog
$end
$timescale
	100ps
$end
$scope module DFF $end
$var wire 1 ! clk $end
$var wire 1 " in $end
$var reg 1 # out $end
$upscope $end
$scope module HalfAdder $end
$var wire 1 $ A $end
$var wire 1 % B $end
$var wire 1 & Cin $end
$var wire 1 ' Cout $end
$var wire 1 ( Y $end
$var wire 1 ) o1 $end
$var wire 1 * o2 $end
$var wire 1 + o3 $end
$upscope $end
$scope module IP_tb $end
$var wire 32 , Result [31:0] $end
$var wire 1 - Finish $end
$var wire 1 . En $end
$var wire 10 / Addr [9:0] $end
$var reg 32 0 Data [31:0] $end
$var reg 1 1 Start $end
$var reg 1 2 clk $end
$var reg 10 3 maxSize [9:0] $end
$var reg 1 4 rst_n $end
$scope module vip $end
$var wire 1 5 Cin $end
$var wire 32 6 Data [31:0] $end
$var wire 1 1 Start $end
$var wire 1 2 clk $end
$var wire 1 4 rst_n $end
$var wire 1 7 Z $end
$var wire 32 8 Y [31:0] $end
$var wire 1 9 V $end
$var wire 1 : N $end
$var wire 4 ; FS [3:0] $end
$var wire 1 < C $end
$var wire 32 = B [31:0] $end
$var wire 32 > A [31:0] $end
$var reg 10 ? Addr [9:0] $end
$var reg 1 . En $end
$var reg 1 - Finish $end
$var reg 32 @ Result [31:0] $end
$var reg 32 A amt [31:0] $end
$var reg 32 B nextAmt [31:0] $end
$var reg 32 C nextRomX [31:0] $end
$var reg 2 D nextState [1:0] $end
$var reg 32 E nextSum [31:0] $end
$var reg 10 F prevAddr [9:0] $end
$var reg 32 G prevResult [31:0] $end
$var reg 32 H romX [31:0] $end
$var reg 2 I state [1:0] $end
$var reg 32 J sum [31:0] $end
$scope module AddMul $end
$var wire 32 K A [31:0] $end
$var wire 32 L B [31:0] $end
$var wire 1 5 Cin $end
$var wire 4 M FS [3:0] $end
$var wire 32 N tmpB [31:0] $end
$var wire 32 O tmpA [31:0] $end
$var wire 1 P mode $end
$var wire 1 Q cin $end
$var wire 32 R Yt [31:0] $end
$var wire 1 S Cout $end
$var reg 1 < C $end
$var reg 1 : N $end
$var reg 1 9 V $end
$var reg 32 T Y [31:0] $end
$var reg 1 7 Z $end
$scope module AddSub $end
$var wire 32 U A [31:0] $end
$var wire 32 V B [31:0] $end
$var wire 32 W Bx [31:0] $end
$var wire 1 Q Cin $end
$var wire 32 X Y [31:0] $end
$var wire 1 P mode $end
$var wire 1 S Cout $end
$var wire 33 Y C [32:0] $end
$upscope $end
$upscope $end
$upscope $end
$upscope $end
$enddefinitions $end
#0
$dumpvars
bx0 Y
bx X
bx W
bx V
bx U
bx T
xS
bx R
0Q
0P
bx O
bx N
bx00 M
bx L
bx K
bx J
bx I
bx H
bx G
bx F
bx E
bx D
bx C
bx B
bx A
bx @
bx ?
bx >
bx =
0<
bx00 ;
x:
09
bx 8
x7
bz 6
z5
14
b1111111111 3
02
01
bz 0
bx /
x.
x-
bx ,
x+
x*
x)
x(
x'
z&
z%
z$
x#
z"
z!
$end
#120
12
#240
b0 ,
b0 @
0-
1.
b0 D
04
02
#360
12
#480
0S
b0 Y
b0 N
b0 W
x9
0<
b0 =
b0 L
b0 V
b100 ;
b100 M
b0 G
b0 I
02
#600
b1111111111 /
b1111111111 ?
12
#720
b1111111111 F
b11001000 0
b11001000 6
11
02
14
#840
b1 D
b0 /
b0 ?
b11001000 B
12
#960
b11111111111111111111111111110110 0
b11111111111111111111111111110110 6
b0 F
b11001000 A
b1 I
02
#1080
b10 D
b11000111 B
b1 /
b1 ?
b11111111111111111111111111110110 C
12
#1200
1S
b111111111111111111111111111100000 Y
07
1:
b111 R
b111 X
b11111111111111111111111101010110 8
b11111111111111111111111101010110 T
b11111111111111111111111111110110 O
b10001 N
b10001 W
09
b11111111111111111111111111110110 >
b11111111111111111111111111110110 K
b11111111111111111111111111110110 U
b10001 =
b10001 L
b10001 V
b1000 ;
b1000 M
b1 F
b11000111 A
b11111111111111111111111111110110 H
b10 I
b10001 0
b10001 6
02
#1320
b11 D
b11111111111111111111111101010110 E
b10 /
b10 ?
b11000110 B
12
#1440
0S
b0 Y
b11111111111111111111111101010110 R
b11111111111111111111111101010110 X
1:
b11111111111111111111111101010110 O
b0 N
b0 W
b11111111111111111111111101010110 8
b11111111111111111111111101010110 T
0<
b11111111111111111111111101010110 >
b11111111111111111111111101010110 K
b11111111111111111111111101010110 U
b0 =
b0 L
b0 V
b100 ;
b100 M
b11111111111111111111111111011110 0
b11111111111111111111111111011110 6
b10 F
b11000110 A
b11111111111111111111111101010110 J
b11 I
02
#1560
b11111111111111111111111101010110 ,
b11111111111111111111111101010110 @
b10 D
b11000101 B
b11 /
b11 ?
b11111111111111111111111111011110 C
12
#1680
1S
b111111111111111111111111111111000 Y
b11111111111111111111111111001011 R
b11111111111111111111111111001011 X
07
0:
b11111111111111111111111111011110 O
b11111111111111111111111111101101 N
b11111111111111111111111111101101 W
b1010000110 8
b1010000110 T
b11111111111111111111111111011110 >
b11111111111111111111111111011110 K
b11111111111111111111111111011110 U
b11111111111111111111111111101101 =
b11111111111111111111111111101101 L
b11111111111111111111111111101101 V
b1000 ;
b1000 M
b11111111111111111111111101010110 G
b11 F
b11000101 A
b11111111111111111111111111011110 H
b10 I
b11111111111111111111111111101101 0
b11111111111111111111111111101101 6
02
#1800
b11 D
b1010000110 E
b100 /
b100 ?
b11000100 B
12
#1920
b111111111111111111111110000001100 Y
b111011100 R
b111011100 X
0:
b1010000110 O
b11111111111111111111111101010110 N
b11111111111111111111111101010110 W
b111011100 8
b111011100 T
1<
b1010000110 >
b1010000110 K
b1010000110 U
b11111111111111111111111101010110 =
b11111111111111111111111101010110 L
b11111111111111111111111101010110 V
b100 ;
b100 M
b11111111111111111111111111101001 0
b11111111111111111111111111101001 6
b100 F
b11000100 A
b1010000110 J
b11 I
02
#2040
b111011100 ,
b111011100 @
b10 D
b11000011 B
b101 /
b101 ?
b11111111111111111111111111101001 C
12
#2160
1S
b111111111111111111111111111000000 Y
b1101 R
b1101 X
1:
b11111111111111111111111111101001 O
b100100 N
b100100 W
b11111111111111111111110011000100 8
b11111111111111111111110011000100 T
0<
b11111111111111111111111111101001 >
b11111111111111111111111111101001 K
b11111111111111111111111111101001 U
b100100 =
b100100 L
b100100 V
b1000 ;
b1000 M
b111011100 G
b101 F
b11000011 A
b11111111111111111111111111101001 H
b10 I
b100100 0
b100100 6
02
#2280
b11 D
b11111111111111111111110011000100 E
b110 /
b110 ?
b11000010 B
12
#2400
0S
b1110111000 Y
b11111111111111111111111010100000 R
b11111111111111111111111010100000 X
1:
b11111111111111111111110011000100 O
b111011100 N
b111011100 W
b11111111111111111111111010100000 8
b11111111111111111111111010100000 T
0<
b11111111111111111111110011000100 >
b11111111111111111111110011000100 K
b11111111111111111111110011000100 U
b111011100 =
b111011100 L
b111011100 V
b100 ;
b100 M
b101 0
b101 6
b110 F
b11000010 A
b11111111111111111111110011000100 J
b11 I
02
#2520
b11111111111111111111111010100000 ,
b11111111111111111111111010100000 @
b10 D
b11000001 B
b111 /
b111 ?
b101 C
12
#2640
0:
b0 Y
b101111 R
b101111 X
b101 O
b101010 N
b101010 W
b11010010 8
b11010010 T
b101 >
b101 K
b101 U
b101010 =
b101010 L
b101010 V
b1000 ;
b1000 M
b11111111111111111111111010100000 G
b111 F
b11000001 A
b101 H
b10 I
b101010 0
b101010 6
02
#2760
b11 D
b11010010 E
b1000 /
b1000 ?
b11000000 B
12
#2880
1:
b100000000 Y
b11111111111111111111111101110010 R
b11111111111111111111111101110010 X
b11010010 O
b11111111111111111111111010100000 N
b11111111111111111111111010100000 W
b11111111111111111111111101110010 8
b11111111111111111111111101110010 T
b11010010 >
b11010010 K
b11010010 U
b11111111111111111111111010100000 =
b11111111111111111111111010100000 L
b11111111111111111111111010100000 V
b100 ;
b100 M
b11101 0
b11101 6
b1000 F
b11000000 A
b11010010 J
b11 I
02
#3000
b11111111111111111111111101110010 ,
b11111111111111111111111101110010 @
b10 D
b10111111 B
b1001 /
b1001 ?
b11101 C
12
#3120
b111000 Y
0:
b101011 R
b101011 X
b11101 O
b1110 N
b1110 W
b110010110 8
b110010110 T
b11101 >
b11101 K
b11101 U
b1110 =
b1110 L
b1110 V
b1000 ;
b1000 M
b11111111111111111111111101110010 G
b1001 F
b10111111 A
b11101 H
b10 I
b1110 0
b1110 6
02
#3240
b11 D
b110010110 E
b1010 /
b1010 ?
b10111110 B
12
#3360
1<
1S
0:
b111111111111111111111111111101100 Y
b100001000 R
b100001000 X
b110010110 O
b11111111111111111111111101110010 N
b11111111111111111111111101110010 W
b100001000 8
b100001000 T
b110010110 >
b110010110 K
b110010110 U
b11111111111111111111111101110010 =
b11111111111111111111111101110010 L
b11111111111111111111111101110010 V
b100 ;
b100 M
b11111111111111111111111111111001 0
b11111111111111111111111111111001 6
b1010 F
b10111110 A
b110010110 J
b11 I
02
#3480
b100001000 ,
b100001000 @
b10 D
b10111101 B
b1011 /
b1011 ?
b11111111111111111111111111111001 C
12
#3600
b111111111111111111111111111100110 Y
b11111111111111111111111111101100 R
b11111111111111111111111111101100 X
0:
b11111111111111111111111111111001 O
b11111111111111111111111111110011 N
b11111111111111111111111111110011 W
b1011011 8
b1011011 T
0<
b11111111111111111111111111111001 >
b11111111111111111111111111111001 K
b11111111111111111111111111111001 U
b11111111111111111111111111110011 =
b11111111111111111111111111110011 L
b11111111111111111111111111110011 V
b1000 ;
b1000 M
b100001000 G
b1011 F
b10111101 A
b11111111111111111111111111111001 H
b10 I
b11111111111111111111111111110011 0
b11111111111111111111111111110011 6
02
#3720
b11 D
b1011011 E
b1100 /
b1100 ?
b10111100 B
12
#3840
0S
b110000 Y
b101100011 R
b101100011 X
09
0:
b1011011 O
b100001000 N
b100001000 W
b101100011 8
b101100011 T
0<
b1011011 >
b1011011 K
b1011011 U
b100001000 =
b100001000 L
b100001000 V
b100 ;
b100 M
b1 0
b1 6
b1100 F
b10111100 A
b1011011 J
b11 I
02
#3960
b101100011 ,
b101100011 @
b10 D
b10111011 B
b1101 /
b1101 ?
b1 C
12
#4080
b110 Y
b100100 R
b100100 X
b1 O
b100011 N
b100011 W
b100011 8
b100011 T
b1 >
b1 K
b1 U
b100011 =
b100011 L
b100011 V
b1000 ;
b1000 M
b101100011 G
b1101 F
b10111011 A
b1 H
b10 I
b100011 0
b100011 6
02
#4200
b11 D
b100011 E
b1110 /
b1110 ?
b10111010 B
12
#4320
b11000110 Y
b110000110 R
b110000110 X
b100011 O
b101100011 N
b101100011 W
b110000110 8
b110000110 T
b100011 >
b100011 K
b100011 U
b101100011 =
b101100011 L
b101100011 V
b100 ;
b100 M
b1110 0
b1110 6
b1110 F
b10111010 A
b100011 J
b11 I
02
#4440
b110000110 ,
b110000110 @
b10 D
b10111001 B
b1111 /
b1111 ?
b1110 C
12
#4560
0S
1:
b11000 Y
b11111111111111111111111111111010 R
b11111111111111111111111111111010 X
b1110 O
b11111111111111111111111111101100 N
b11111111111111111111111111101100 W
b11111111111111111111111011101000 8
b11111111111111111111111011101000 T
b1110 >
b1110 K
b1110 U
b11111111111111111111111111101100 =
b11111111111111111111111111101100 L
b11111111111111111111111111101100 V
b1000 ;
b1000 M
b110000110 G
b1111 F
b10111001 A
b1110 H
b10 I
b11111111111111111111111111101100 0
b11111111111111111111111111101100 6
02
#4680
b11 D
b11111111111111111111111011101000 E
b10000 /
b10000 ?
b10111000 B
12
#4800
1<
1S
0:
b111111111111111111111111100000000 Y
b1101110 R
b1101110 X
b11111111111111111111111011101000 O
b110000110 N
b110000110 W
b1101110 8
b1101110 T
b11111111111111111111111011101000 >
b11111111111111111111111011101000 K
b11111111111111111111111011101000 U
b110000110 =
b110000110 L
b110000110 V
b100 ;
b100 M
b11111111111111111111111111100110 0
b11111111111111111111111111100110 6
b10000 F
b10111000 A
b11111111111111111111111011101000 J
b11 I
02
#4920
b1101110 ,
b1101110 @
b10 D
b10110111 B
b10001 /
b10001 ?
b11111111111111111111111111100110 C
12
#5040
0S
b0 Y
b11111111111111111111111111101110 R
b11111111111111111111111111101110 X
1:
b11111111111111111111111111100110 O
b1000 N
b1000 W
b11111111111111111111111100110000 8
b11111111111111111111111100110000 T
0<
b11111111111111111111111111100110 >
b11111111111111111111111111100110 K
b11111111111111111111111111100110 U
b1000 =
b1000 L
b1000 V
b1000 ;
b1000 M
b1101110 G
b10001 F
b10110111 A
b11111111111111111111111111100110 H
b10 I
b1000 0
b1000 6
02
#5160
b11 D
b11111111111111111111111100110000 E
b10010 /
b10010 ?
b10110110 B
12
#5280
b11000000 Y
b11111111111111111111111110011110 R
b11111111111111111111111110011110 X
b11111111111111111111111100110000 O
b1101110 N
b1101110 W
b11111111111111111111111110011110 8
b11111111111111111111111110011110 T
b11111111111111111111111100110000 >
b11111111111111111111111100110000 K
b11111111111111111111111100110000 U
b1101110 =
b1101110 L
b1101110 V
b100 ;
b100 M
b100011 0
b100011 6
b10010 F
b10110110 A
b11111111111111111111111100110000 J
b11 I
02
#5400
b11111111111111111111111110011110 ,
b11111111111111111111111110011110 @
b10 D
b10110101 B
b10011 /
b10011 ?
b100011 C
12
#5520
0:
b1100 Y
b111001 R
b111001 X
b100011 O
b10110 N
b10110 W
b1100000010 8
b1100000010 T
b100011 >
b100011 K
b100011 U
b10110 =
b10110 L
b10110 V
b1000 ;
b1000 M
b11111111111111111111111110011110 G
b10011 F
b10110101 A
b100011 H
b10 I
b10110 0
b10110 6
02
#5640
b11 D
b1100000010 E
b10100 /
b10100 ?
b10110100 B
12
#5760
1<
1S
0:
b111111111111111111111111000111100 Y
b1010100000 R
b1010100000 X
b1100000010 O
b11111111111111111111111110011110 N
b11111111111111111111111110011110 W
b1010100000 8
b1010100000 T
b1100000010 >
b1100000010 K
b1100000010 U
b11111111111111111111111110011110 =
b11111111111111111111111110011110 L
b11111111111111111111111110011110 V
b100 ;
b100 M
b1 0
b1 6
b10100 F
b10110100 A
b1100000010 J
b11 I
02
#5880
b1010100000 ,
b1010100000 @
b10 D
b10110011 B
b10101 /
b10101 ?
b1 C
12
#6000
0S
b110 Y
b100100 R
b100100 X
0:
b1 O
b100011 N
b100011 W
b100011 8
b100011 T
0<
b1 >
b1 K
b1 U
b100011 =
b100011 L
b100011 V
b1000 ;
b1000 M
b1010100000 G
b10101 F
b10110011 A
b1 H
b10 I
b100011 0
b100011 6
02
#6120
b11 D
b100011 E
b10110 /
b10110 ?
b10110010 B
12
#6240
b1000000 Y
b1011000011 R
b1011000011 X
b100011 O
b1010100000 N
b1010100000 W
b1011000011 8
b1011000011 T
b100011 >
b100011 K
b100011 U
b1010100000 =
b1010100000 L
b1010100000 V
b100 ;
b100 M
b11111111111111111111111111100100 0
b11111111111111111111111111100100 6
b10110 F
b10110010 A
b100011 J
b11 I
02
#6360
b1011000011 ,
b1011000011 @
b10 D
b10110001 B
b10111 /
b10111 ?
b11111111111111111111111111100100 C
12
#6480
1S
b111111111111111111111111111001000 Y
b11111111111111111111111111001000 R
b11111111111111111111111111001000 X
b11111111111111111111111111100100 O
b11111111111111111111111111100100 N
b11111111111111111111111111100100 W
b1100010000 8
b1100010000 T
b11111111111111111111111111100100 >
b11111111111111111111111111100100 K
b11111111111111111111111111100100 U
b11111111111111111111111111100100 =
b11111111111111111111111111100100 L
b11111111111111111111111111100100 V
b1000 ;
b1000 M
b1011000011 G
b10111 F
b10110001 A
b11111111111111111111111111100100 H
b10 I
02
#6600
b11 D
b1100010000 E
b11000 /
b11000 ?
b10110000 B
12
#6720
0S
b10000000000 Y
b10111010011 R
b10111010011 X
09
0:
b1100010000 O
b1011000011 N
b1011000011 W
b10111010011 8
b10111010011 T
0<
b1100010000 >
b1100010000 K
b1100010000 U
b1011000011 =
b1011000011 L
b1011000011 V
b100 ;
b100 M
b11111111111111111111111111110000 0
b11111111111111111111111111110000 6
b11000 F
b10110000 A
b1100010000 J
b11 I
02
#6840
b10111010011 ,
b10111010011 @
b10 D
b10101111 B
b11001 /
b11001 ?
b11111111111111111111111111110000 C
12
#6960
1S
b111111111111111111111111111000000 Y
b11111111111111111111111111011001 R
b11111111111111111111111111011001 X
b11111111111111111111111111110000 O
b11111111111111111111111111101001 N
b11111111111111111111111111101001 W
b101110000 8
b101110000 T
b11111111111111111111111111110000 >
b11111111111111111111111111110000 K
b11111111111111111111111111110000 U
b11111111111111111111111111101001 =
b11111111111111111111111111101001 L
b11111111111111111111111111101001 V
b1000 ;
b1000 M
b10111010011 G
b11001 F
b10101111 A
b11111111111111111111111111110000 H
b10 I
b11111111111111111111111111101001 0
b11111111111111111111111111101001 6
02
#7080
b11 D
b101110000 E
b11010 /
b11010 ?
b10101110 B
12
#7200
0S
b1111100000 Y
b11101000011 R
b11101000011 X
09
0:
b101110000 O
b10111010011 N
b10111010011 W
b11101000011 8
b11101000011 T
0<
b101110000 >
b101110000 K
b101110000 U
b10111010011 =
b10111010011 L
b10111010011 V
b100 ;
b100 M
b110 0
b110 6
b11010 F
b10101110 A
b101110000 J
b11 I
02
#7320
b11101000011 ,
b11101000011 @
b10 D
b10101101 B
b11011 /
b11011 ?
b110 C
12
#7440
b11100 Y
b110100 R
b110100 X
b110 O
b101110 N
b101110 W
b100010100 8
b100010100 T
b110 >
b110 K
b110 U
b101110 =
b101110 L
b101110 V
b1000 ;
b1000 M
b11101000011 G
b11011 F
b10101101 A
b110 H
b10 I
b101110 0
b101110 6
02
#7560
b11 D
b100010100 E
b11100 /
b11100 ?
b10101100 B
12
#7680
b111000000000 Y
b100001010111 R
b100001010111 X
b100010100 O
b11101000011 N
b11101000011 W
b100001010111 8
b100001010111 T
b100010100 >
b100010100 K
b100010100 U
b11101000011 =
b11101000011 L
b11101000011 V
b100 ;
b100 M
b100001 0
b100001 6
b11100 F
b10101100 A
b100010100 J
b11 I
02
#7800
b100001010111 ,
b100001010111 @
b10 D
b10101011 B
b11101 /
b11101 ?
b100001 C
12
#7920
1S
1:
b111111111111111111111111111000010 Y
b10110 R
b10110 X
b100001 O
b11111111111111111111111111110101 N
b11111111111111111111111111110101 W
b11111111111111111111111010010101 8
b11111111111111111111111010010101 T
b100001 >
b100001 K
b100001 U
b11111111111111111111111111110101 =
b11111111111111111111111111110101 L
b11111111111111111111111111110101 V
b1000 ;
b1000 M
b100001010111 G
b11101 F
b10101011 A
b100001 H
b10 I
b11111111111111111111111111110101 0
b11111111111111111111111111110101 6
02
#8040
b11 D
b11111111111111111111111010010101 E
b11110 /
b11110 ?
b10101010 B
12
#8160
b111111111111111111111000000101110 Y
b11011101100 R
b11011101100 X
0:
b11111111111111111111111010010101 O
b100001010111 N
b100001010111 W
b11011101100 8
b11011101100 T
1<
b11111111111111111111111010010101 >
b11111111111111111111111010010101 K
b11111111111111111111111010010101 U
b100001010111 =
b100001010111 L
b100001010111 V
b100 ;
b100 M
b11111111111111111111111111110110 0
b11111111111111111111111111110110 6
b11110 F
b10101010 A
b11111111111111111111111010010101 J
b11 I
02
#8280
b11011101100 ,
b11011101100 @
b10 D
b10101001 B
b11111 /
b11111 ?
b11111111111111111111111111110110 C
12
#8400
b111111111111111111111111111101000 Y
b11111111111111111111111111101011 R
b11111111111111111111111111101011 X
0:
b11111111111111111111111111110110 O
b11111111111111111111111111110101 N
b11111111111111111111111111110101 W
b1101110 8
b1101110 T
0<
b11111111111111111111111111110110 >
b11111111111111111111111111110110 K
b11111111111111111111111111110110 U
b11111111111111111111111111110101 =
b11111111111111111111111111110101 L
b11111111111111111111111111110101 V
b1000 ;
b1000 M
b11011101100 G
b11111 F
b10101001 A
b11111111111111111111111111110110 H
b10 I
b11111111111111111111111111110101 0
b11111111111111111111111111110101 6
02
#8520
b11 D
b1101110 E
b100000 /
b100000 ?
b10101000 B
12
#8640
0S
b111011000 Y
b11101011010 R
b11101011010 X
09
0:
b1101110 O
b11011101100 N
b11011101100 W
b11101011010 8
b11101011010 T
0<
b1101110 >
b1101110 K
b1101110 U
b11011101100 =
b11011101100 L
b11011101100 V
b100 ;
b100 M
b100111 0
b100111 6
b100000 F
b10101000 A
b1101110 J
b11 I
02
#8760
b11101011010 ,
b11101011010 @
b10 D
b10100111 B
b100001 /
b100001 ?
b100111 C
12
#8880
1S
1:
b111111111111111111111111111001000 Y
b1011 R
b1011 X
b100111 O
b11111111111111111111111111100100 N
b11111111111111111111111111100100 W
b11111111111111111111101110111100 8
b11111111111111111111101110111100 T
b100111 >
b100111 K
b100111 U
b11111111111111111111111111100100 =
b11111111111111111111111111100100 L
b11111111111111111111111111100100 V
b1000 ;
b1000 M
b11101011010 G
b100001 F
b10100111 A
b100111 H
b10 I
b11111111111111111111111111100100 0
b11111111111111111111111111100100 6
02
#9000
b11 D
b11111111111111111111101110111100 E
b100010 /
b100010 ?
b10100110 B
12
#9120
b111111111111111111111111111110000 Y
b1100010110 R
b1100010110 X
0:
b11111111111111111111101110111100 O
b11101011010 N
b11101011010 W
b1100010110 8
b1100010110 T
1<
b11111111111111111111101110111100 >
b11111111111111111111101110111100 K
b11111111111111111111101110111100 U
b11101011010 =
b11101011010 L
b11101011010 V
b100 ;
b100 M
b11111111111111111111111111010110 0
b11111111111111111111111111010110 6
b100010 F
b10100110 A
b11111111111111111111101110111100 J
b11 I
02
