Local/ALU.v
module ALU(A, B, Cin, FS, Y, N, C, V, Z);
	parameter n = 32;
	input [n-1:0] A, B;
	input Cin;
	input [3:0] FS;

	output reg [n-1:0] Y;
	output reg N, C, V, Z;

	wire [n-1:0] Yt;
	wire Cout;
	wire mode;
	wire cin;

	wire [n-1:0] tmpA, tmpB;
	assign tmpA[15:0] = A[15:0];
	assign tmpB[15:0] = B[15:0];
	assign tmpA[n-1:16] = {n-16{A[15]}};
	assign tmpB[n-1:16] = {n-16{B[15]}};

	AdderSubstractor AddSub(A, B, cin, mode, Cout, Yt);

	assign cin = (FS==4'b0101) ? Cin : 1'b0 ;
	assign mode = (FS==4'b0110||FS==4'b0111) ? 1'b1 : 1'b0 ;

	always@(*)begin
		N = Y[n-1];
		Z = (Y==32'd0)?1'b1:1'b0;
		case(FS)
			4'b0000, 4'b0010,
			4'b1100, 4'b1101, 4'b1110, 4'b1111:begin
				N = 1'b0;
				Z = 1'b0;
			end
		endcase
	end

	always@(*)begin
		C = 1'b0;
		V = 1'b0;
		case(FS)
			4'b0001:begin
				C = A[n-1];
				V = A[n-1] ^ A[n-2];					
			end
			4'b0100, 4'b0101, 
			4'b0110, 4'b0111:begin
				C = Cout;
				V =
				  (	( (A[n-1]==1'b1) & (B[n-1]==1'b0) & (mode==1'b1) & (Y[n-1]==1'b0) ) |
					( (A[n-1]==1'b0) & (B[n-1]==1'b1) & (mode==1'b1) & (Y[n-1]==1'b1) ) |
					( (A[n-1]==1'b1) & (B[n-1]==1'b1) & (mode==1'b0) & (Y[n-1]==1'b0) ) |
					( (A[n-1]==1'b0) & (B[n-1]==1'b0) & (mode==1'b0) & (Y[n-1]==1'b1) ) ) ?
				  		1'b1 : 1'b0 ;
			end
		endcase
	end

	always@(*)begin
		case(FS)
			// logic left shift
			4'b0000:begin
				Y[n-1:1] = A[n-2:0];
				Y[0] = 1'b0;
			end
			// arithmetic left shift 
			4'b0001:begin
				Y[n-1:1] = A[n-2:0];
				Y[0] = 1'b0;

			end
			// srl
			4'b0010:begin
				Y[n-2:0] = A[n-1:1];
				Y[n-1] = 1'b0;
			end
			// sra
			4'b0011:begin
				Y[n-2:0] = A[n-1:1];
				Y[n-1] = (Y[n-2]==1'b1)?1'b1:1'b0;
			end
			// add
			4'b0100:begin
				Y = Yt;
			end
			// add with carry
			4'b0101:begin
				Y = Yt;
			end
			// sub
			4'b0110:begin
				Y = Yt;
			end
			// abs
			4'b0111:begin
				Y = (Yt[n-1]==1'b1) ? (Yt ^ {n{1'b1}}) + 1 : Yt ;
			end
			// multi
			4'b1000:begin
				Y = tmpA * tmpB;
			end
			// zero
			4'b1001:begin
				Y = 32'd0;
			end
			// output A
			4'b1010:begin
				Y = A;
			end
			// output B
			4'b1011:begin
				Y = B;
			end
			// and
			4'b1100:begin
				Y = A & B;
			end
			// or
			4'b1101:begin
				Y = A | B;
			end
			// xor
			4'b1110:begin
				Y = A ^ B;
			end
			// not
			4'b1111:begin
				Y = ~A;
			end
		endcase
	end

endmodule

module HalfAdder(A, B, Cin, Cout, Y);
	input A, B, Cin;
	output Cout, Y;

	wire o1, o2, o3;

	xor xor1(Y, A, B, Cin);
	and and1(o1, A, B);
	and and2(o2, A, Cin);
	and and3(o3, B, Cin);
	or or1(Cout, o1, o2, o3);
endmodule

module AdderSubstractor(A, B, Cin, mode, Cout, Y);
	parameter n = 32;
	input [n-1:0] A, B;
	input mode, Cin;
	output Cout;
	output [n-1:0] Y;

	wire Cout;
	wire [n-1:0] Bx;
	wire [n:0] C;

	assign C[0] = mode | Cin;
	assign Bx = B ^ {n{mode}};
	assign Y = A ^ Bx ^ C[n-1:0];
	assign C[n:1] = A & Bx | A & C[n-1:0] | Bx & C[n-1:0];
	assign Cout = C[n];
endmodule

Bonus/Cost_tb.v
`define SDFFILE   "./VIP.sdf"
`define End_CYCLE  1000000000

`define info  "./info_bonus.dat"   

module IP_tb;
	//Clock period
	parameter cyc = 24;
	
	parameter dataWidth=32;
	parameter memWidth=10;

	// #pattern
	parameter PAT = 1026;

	reg [dataWidth-1:0]dataROM[0:PAT-1];
	reg [memWidth-1:0]maxSize;

	reg clk, rst_n, Start;
	reg [dataWidth-1:0]Data;
	wire Finish, En;
	wire [dataWidth-1:0]Result;
	wire [memWidth-1:0]Addr;

	//VIP module
	Cost cost( 
		.clk(clk),
		.rst_n(rst_n), 
		.Start(Start), 
		.Data(Data),
		.Addr(Addr),
		.Result(Result),
		.Finish(Finish),
		.En(En)
	);
	
	always #(cyc/2) clk = ~clk;
	
	initial begin
		`ifdef SDF
			$sdf_annotate(`SDFFILE, vip);
			$dumpfile("Cost_syn.vcd");
		`else
			$dumpfile("Cost.vcd");
		`endif
		$dumpvars;
	end

	
	initial begin
		
		//Init ROM
		$readmemb ("info_bonus.dat", dataROM);

		maxSize = 10'd1023;
	
		rst_n = 1'b1;
		clk = 1'b0;
		Start = 1'b0;
		Data = 'hz;

		@(negedge clk)  rst_n = 1'b0; 
		#(cyc*2);    rst_n = 1'b1; 
		
		@(negedge clk)  Start = 1'b1;
		while (Finish == 0) begin             
			if(En && Addr <= maxSize) begin
				Data = dataROM[Addr];  
				
			end else begin
				Data = 'hz;  
		
			end                    
			@(negedge clk);  

		end 
		$display(" ");
		if($signed(Result) == $signed(dataROM[1024]))begin
			$display("Congratulations !! :)");
			$display(" ");
			$finish;

		end

		$display("Wrong Answer !! :(");
	    $display("Result = %d, Answer = %d", $signed(Result), $signed(dataROM[1024]));
		$display(" ");
		$finish;
	end
	
	initial  begin
		#`End_CYCLE ;
		$display("-----------------------------------------------------\n");
		$display("Error!!! Somethings' wrong with your code ...!\n");
		$display("-------------------------FAIL------------------------\n");
		$display("-----------------------------------------------------\n");
		$finish;
	end

endmodule

Bonus/Cost.v
module Cost(clk, rst_n, Start, Data, Addr, Result, Finish, En);

	parameter memWidth = 10;
	parameter dataWidth = 32;

	input clk, rst_n, Start;
	input [dataWidth-1:0]Data;

	output reg [dataWidth-1:0]Result;
	output reg [memWidth-1:0]Addr;
	output reg Finish, En;

	// d flip-flop
	reg  [dataWidth-1:0] nextRomX, nextRomY, nextSum, nextAmt;
	reg  [dataWidth-1:0] romX, romY, sum, prevResult, amt;	// wire
	reg  [memWidth-1:0]  prevAddr;	// wire
	reg  [2:0] state;	// wire
	reg  [2:0] nextState;
	/*DFF #(3) 		status(clk, nextState, 		 state);
	DFF #(dataWidth)    r0(clk,  nextRomX, 		  romX);
	DFF #(dataWidth)   Acc(clk,    Result,  prevResult);
	DFF #(memWidth) memRAM(clk, 	 Addr, 	  prevAddr);
	DFF #(dataWidth)  temp(clk,   nextSum, 		   sum);
	DFF #(dataWidth)  left(clk,   nextAmt, 		   amt);*/
	always@(negedge clk)begin	// a big combined D-flipflop
		state = nextState ;
		romX  =  nextRomX ;
		romY  =  nextRomY ;
		sum   =   nextSum ;
		amt   =   nextAmt ;
		prevAddr   = Addr ;
		prevResult = Result ;
	end

	// states
	parameter IDLE = 3'b000;
	parameter X_0  = 3'b001;
	parameter SUB  = 3'b010;
	parameter SQR  = 3'b011;
	parameter ADD  = 3'b100;
	parameter SHFT = 3'b101;

	// ALU
	wire [dataWidth-1:0] Y;
	reg  [dataWidth-1:0] A, B;
	reg  [3:0] FS;
	wire Cin, N, C, V, Z;
	always@(*)begin
		case(state)
			SUB:begin
				A  = romX ;
				B  = Data ;
				FS = 4'b0110 ;
				end
			SQR:begin
				A  = sum ;
				B  = sum ;
				FS = 4'b1000 ;
				end
			ADD:begin
				A  = sum ;
				B  = prevResult ;
				FS = 4'b0100 ;
				end
			SHFT:begin
				A  = prevResult;
				FS = 4'b0011;
				end
		endcase
	end
	ALU AddMul(A, B, Cin, FS, Y, N, C, V, Z);

	// finite state machine
	always@(posedge clk)begin
		if (!rst_n) begin	// initialize
			nextState = IDLE;
			En = 1;
			Finish = 0;
			Result = 0;
		end
	end
	always@(posedge clk)begin
		case(state)
			IDLE:begin
				Addr = 10'd1023;
				if (Start)begin
					nextAmt = Data;
					Addr = 0;
					nextState = X_0;
				end else begin
					nextState = IDLE;
					end
				end
			X_0:begin
				nextRomX = Data;
				Addr = prevAddr + 1;	// ask for next Y
				nextAmt = amt - 1;
				nextState = SUB;
				end
			SUB:begin
				nextSum = Y;	// ALU
				nextState = SQR;
				end
			SQR:begin
				nextRomX = Data;
				nextAmt = amt - 1;	// ask for next X
				Addr = prevAddr + 1 ;
				nextSum = Y;
				nextState = ADD;
				end
			ADD:begin
				if (amt == 0)begin
					nextState = SHFT;
				end else begin
					nextRomX = Data;
					Addr = prevAddr + 1 ;
					nextAmt = amt - 1;
					nextState = SUB;
				end
				Result = Y;
				end
			SHFT:begin
				En = 0;
				Finish = 1;
				Result = Y;
				end
		endcase
	end
	
endmodule

module DFF(clk, in, out);
	parameter n = 1;
	input clk;
	input [n-1:0] in ;
	output reg [n-1:0] out ;
	
	always @(negedge clk)
		out = in ;
endmodule

Bonus/Cost.vcd
$date
	Mon Apr 17 13:40:26 2017
$end
$version
	Icarus Verilog
$end
$timescale
	100ps
$end
$scope module DFF $end
$var wire 1 ! clk $end
$var wire 1 " in $end
$var reg 1 # out $end
$upscope $end
$scope module HalfAdder $end
$var wire 1 $ A $end
$var wire 1 % B $end
$var wire 1 & Cin $end
$var wire 1 ' Cout $end
$var wire 1 ( Y $end
$var wire 1 ) o1 $end
$var wire 1 * o2 $end
$var wire 1 + o3 $end
$upscope $end
$scope module IP_tb $end
$var wire 32 , Result [31:0] $end
$var wire 1 - Finish $end
$var wire 1 . En $end
$var wire 10 / Addr [9:0] $end
$var reg 32 0 Data [31:0] $end
$var reg 1 1 Start $end
$var reg 1 2 clk $end
$var reg 10 3 maxSize [9:0] $end
$var reg 1 4 rst_n $end
$scope module cost $end
$var wire 1 5 Cin $end
$var wire 32 6 Data [31:0] $end
$var wire 1 1 Start $end
$var wire 1 2 clk $end
$var wire 1 4 rst_n $end
$var wire 1 7 Z $end
$var wire 32 8 Y [31:0] $end
$var wire 1 9 V $end
$var wire 1 : N $end
$var wire 1 ; C $end
$var reg 32 < A [31:0] $end
$var reg 10 = Addr [9:0] $end
$var reg 32 > B [31:0] $end
$var reg 1 . En $end
$var reg 4 ? FS [3:0] $end
$var reg 1 - Finish $end
$var reg 32 @ Result [31:0] $end
$var reg 32 A amt [31:0] $end
$var reg 32 B nextAmt [31:0] $end
$var reg 32 C nextRomX [31:0] $end
$var reg 32 D nextRomY [31:0] $end
$var reg 3 E nextState [2:0] $end
$var reg 32 F nextSum [31:0] $end
$var reg 10 G prevAddr [9:0] $end
$var reg 32 H prevResult [31:0] $end
$var reg 32 I romX [31:0] $end
$var reg 32 J romY [31:0] $end
$var reg 3 K state [2:0] $end
$var reg 32 L sum [31:0] $end
$scope module AddMul $end
$var wire 32 M A [31:0] $end
$var wire 32 N B [31:0] $end
$var wire 1 5 Cin $end
$var wire 4 O FS [3:0] $end
$var wire 32 P tmpB [31:0] $end
$var wire 32 Q tmpA [31:0] $end
$var wire 1 R mode $end
$var wire 1 S cin $end
$var wire 32 T Yt [31:0] $end
$var wire 1 U Cout $end
$var reg 1 ; C $end
$var reg 1 : N $end
$var reg 1 9 V $end
$var reg 32 V Y [31:0] $end
$var reg 1 7 Z $end
$scope module AddSub $end
$var wire 32 W A [31:0] $end
$var wire 32 X B [31:0] $end
$var wire 32 Y Bx [31:0] $end
$var wire 1 S Cin $end
$var wire 32 Z Y [31:0] $end
$var wire 1 R mode $end
$var wire 1 U Cout $end
$var wire 33 [ C [32:0] $end
$upscope $end
$upscope $end
$upscope $end
$upscope $end
$enddefinitions $end
#0
$dumpvars
bx [
bx Z
bx Y
bx X
bx W
bx V
xU
bx T
xS
xR
bx Q
bx P
bx O
bx N
bx M
bx L
bx K
bx J
bx I
bx H
bx G
bx F
bx E
bx D
bx C
bx B
bx A
bx @
bx ?
bx >
bx =
bx <
0;
x:
09
bx 8
x7
bz 6
z5
14
b1111111111 3
02
01
bz 0
bx /
x.
x-
bx ,
x+
x*
x)
x(
x'
z&
z%
z$
x#
z"
z!
$end
#120
12
#240
04
02
#360
b0 ,
b0 @
0-
1.
b0 E
12
#480
b0 H
b0 K
02
#600
b1111111111 /
b1111111111 =
12
#720
b1111111111 G
b11001000 0
b11001000 6
11
02
14
#840
b1 E
b0 /
b0 =
b11001000 B
12
#960
b10011 0
b10011 6
b0 G
b11001000 A
b1 K
02
#1080
b10 E
b11000111 B
b1 /
b1 =
b10011 C
12
#1200
0U
1:
07
b11111111111111111111111111110010 8
b11111111111111111111111111110010 V
b11111111111111111111111111110010 T
b11111111111111111111111111110010 Z
b11111111111111111111111111011110 Y
b111111 [
1R
0S
b100001 P
b10011 Q
09
0;
b110 ?
b110 O
b100001 >
b100001 N
b100001 X
b10011 <
b10011 M
b10011 W
b1 G
b11000111 A
b10011 I
b10 K
b100001 0
b100001 6
02
#1320
b11 E
b11111111111111111111111111110010 F
12
#1440
1U
b111111111111111111111111111100100 [
0R
b11111111111111111111111111100100 T
b11111111111111111111111111100100 Z
0:
b11111111111111111111111111110010 P
b11111111111111111111111111110010 Y
b11111111111111111111111111110010 Q
b11000100 8
b11000100 V
b1000 ?
b1000 O
b11111111111111111111111111110010 >
b11111111111111111111111111110010 N
b11111111111111111111111111110010 X
b11111111111111111111111111110010 <
b11111111111111111111111111110010 M
b11111111111111111111111111110010 W
b11111111111111111111111111110010 L
b11 K
02
#1560
b100 E
b11000100 F
b10 /
b10 =
b11000110 B
b100001 C
12
#1680
0U
b0 [
b11000100 T
b11000100 Z
0:
b0 P
b0 Y
b11000100 Q
09
0;
b11000100 8
b11000100 V
b100 ?
b100 O
b0 >
b0 N
b0 X
b11000100 <
b11000100 M
b11000100 W
b10 G
b11000110 A
b11000100 L
b100001 I
b100 K
b10011 0
b10011 6
02
#1800
b11000100 ,
b11000100 @
b10 E
b11000101 B
b11 /
b11 =
b10011 C
12
#1920
0;
0U
1:
b1111 [
1R
b11111111111111111111111111111010 8
b11111111111111111111111111111010 V
b11111111111111111111111111111010 T
b11111111111111111111111111111010 Z
b11001 P
b11111111111111111111111111100110 Y
b10011 Q
b110 ?
b110 O
b11001 >
b11001 N
b11001 X
b10011 <
b10011 M
b10011 W
b11001 0
b11001 6
b11000100 H
b11 G
b11000101 A
b10011 I
b10 K
02
#2040
b11 E
b11111111111111111111111111111010 F
12
#2160
1U
b111111111111111111111111111110100 [
0R
b11111111111111111111111111110100 T
b11111111111111111111111111110100 Z
0:
b11111111111111111111111111111010 P
b11111111111111111111111111111010 Y
b11111111111111111111111111111010 Q
b100100 8
b100100 V
b1000 ?
b1000 O
b11111111111111111111111111111010 >
b11111111111111111111111111111010 N
b11111111111111111111111111111010 X
b11111111111111111111111111111010 <
b11111111111111111111111111111010 M
b11111111111111111111111111111010 W
b11111111111111111111111111111010 L
b11 K
02
#2280
b100 E
b100100 F
b100 /
b100 =
b11000100 B
b11001 C
12
#2400
0U
b1000 [
b11101000 T
b11101000 Z
0:
b11000100 P
b11000100 Y
b100100 Q
09
0;
b11101000 8
b11101000 V
b100 ?
b100 O
b11000100 >
b11000100 N
b11000100 X
b100100 <
b100100 M
b100100 W
b10111 0
b10111 6
b100 G
b11000100 A
b100100 L
b11001 I
b100 K
02
#2520
b11101000 ,
b11101000 @
b10 E
b11000011 B
b101 /
b101 =
b10111 C
12
#2640
1;
1U
0:
b111111111111111111111111111111111 [
1R
b10001 8
b10001 V
b10001 T
b10001 Z
b110 P
b11111111111111111111111111111001 Y
b10111 Q
b110 ?
b110 O
b110 >
b110 N
b110 X
b10111 <
b10111 M
b10111 W
b11101000 H
b101 G
b11000011 A
b10111 I
b10 K
b110 0
b110 6
02
#2760
b11 E
b10001 F
12
#2880
0U
b100010 [
0R
b100010 T
b100010 Z
b10001 P
b10001 Y
b10001 Q
0;
b100100001 8
b100100001 V
b1000 ?
b1000 O
b10001 >
b10001 N
b10001 X
b10001 <
b10001 M
b10001 W
b10001 L
b11 K
02
#3000
b100 E
b100100001 F
b110 /
b110 =
b11000010 B
b110 C
12
#3120
b1111000000 [
b1000001001 T
b1000001001 Z
b11101000 P
b11101000 Y
b100100001 Q
b1000001001 8
b1000001001 V
b100 ?
b100 O
b11101000 >
b11101000 N
b11101000 X
b100100001 <
b100100001 M
b100100001 W
b110 G
b11000010 A
b100100001 L
b110 I
b100 K
b11111111111111111111111111011010 0
b11111111111111111111111111011010 6
02
#3240
b1000001001 ,
b1000001001 @
b10 E
b11000001 B
b111 /
b111 =
b11111111111111111111111111011010 C
12
#3360
1;
1U
09
1:
b111111111111111111111111111110101 [
1R
b11111111111111111111111111000101 8
b11111111111111111111111111000101 V
b11111111111111111111111111000101 T
b11111111111111111111111111000101 Z
b10101 P
b11111111111111111111111111101010 Y
b11111111111111111111111111011010 Q
b110 ?
b110 O
b10101 >
b10101 N
b10101 X
b11111111111111111111111111011010 <
b11111111111111111111111111011010 M
b11111111111111111111111111011010 W
b10101 0
b10101 6
b1000001001 H
b111 G
b11000001 A
b11111111111111111111111111011010 I
b10 K
02
#3480
b11 E
b11111111111111111111111111000101 F
12
#3600
0:
b111111111111111111111111110001010 [
0R
b11111111111111111111111110001010 T
b11111111111111111111111110001010 Z
b11111111111111111111111111000101 P
b11111111111111111111111111000101 Y
b11111111111111111111111111000101 Q
0;
b110110011001 8
b110110011001 V
b1000 ?
b1000 O
b11111111111111111111111111000101 >
b11111111111111111111111111000101 N
b11111111111111111111111111000101 X
b11111111111111111111111111000101 <
b11111111111111111111111111000101 M
b11111111111111111111111111000101 W
b11111111111111111111111111000101 L
b11 K
02
#3720
b100 E
b110110011001 F
b1000 /
b1000 =
b11000000 B
b10101 C
12
#3840
0U
b110010 [
b111110100010 T
b111110100010 Z
0:
b1000001001 P
b1000001001 Y
b110110011001 Q
09
0;
b111110100010 8
b111110100010 V
b100 ?
b100 O
b1000001001 >
b1000001001 N
b1000001001 X
b110110011001 <
b110110011001 M
b110110011001 W
b110010 0
b110010 6
b1000 G
b11000000 A
b110110011001 L
b10101 I
b100 K
02
#3960
b111110100010 ,
b111110100010 @
b10 E
b10111111 B
b1001 /
b1001 =
b110010 C
12
#4080
09
0:
b1 [
1R
b111111 8
b111111 V
b111111 T
b111111 Z
b11111111111111111111111111110011 P
b1100 Y
b110010 Q
b110 ?
b110 O
b11111111111111111111111111110011 >
b11111111111111111111111111110011 N
b11111111111111111111111111110011 X
b110010 <
b110010 M
b110010 W
b111110100010 H
b1001 G
b10111111 A
b110010 I
b10 K
b11111111111111111111111111110011 0
b11111111111111111111111111110011 6
02
#4200
b11 E
b111111 F
12
#4320
b1111110 [
0R
b1111110 T
b1111110 Z
0:
b111111 P
b111111 Y
b111111 Q
b111110000001 8
b111110000001 V
b1000 ?
b1000 O
b111111 >
b111111 N
b111111 X
b111111 <
b111111 M
b111111 W
b111111 L
b11 K
02
#4440
b100 E
b111110000001 F
b1010 /
b1010 =
b10111110 B
b11111111111111111111111111110011 C
12
#4560
b1111100000000 [
b1111100100011 T
b1111100100011 Z
b111110100010 P
b111110100010 Y
b111110000001 Q
b1111100100011 8
b1111100100011 V
b100 ?
b100 O
b111110100010 >
b111110100010 N
b111110100010 X
b111110000001 <
b111110000001 M
b111110000001 W
b1010 G
b10111110 A
b111110000001 L
b11111111111111111111111111110011 I
b100 K
b11111111111111111111111111100110 0
b11111111111111111111111111100110 6
02
#4680
b1111100100011 ,
b1111100100011 @
b10 E
b10111101 B
b1011 /
b1011 =
b11111111111111111111111111100110 C
12
#4800
0;
0U
1:
b11111 [
1R
b11111111111111111111111111110110 8
b11111111111111111111111111110110 V
b11111111111111111111111111110110 T
b11111111111111111111111111110110 Z
b11111111111111111111111111110000 P
b1111 Y
b11111111111111111111111111100110 Q
09
b110 ?
b110 O
b11111111111111111111111111110000 >
b11111111111111111111111111110000 N
b11111111111111111111111111110000 X
b11111111111111111111111111100110 <
b11111111111111111111111111100110 M
b11111111111111111111111111100110 W
b11111111111111111111111111110000 0
b11111111111111111111111111110000 6
b1111100100011 H
b1011 G
b10111101 A
b11111111111111111111111111100110 I
b10 K
02
#4920
b11 E
b11111111111111111111111111110110 F
12
#5040
1U
b111111111111111111111111111101100 [
0R
b11111111111111111111111111101100 T
b11111111111111111111111111101100 Z
0:
b11111111111111111111111111110110 P
b11111111111111111111111111110110 Y
b11111111111111111111111111110110 Q
b1100100 8
b1100100 V
b1000 ?
b1000 O
b11111111111111111111111111110110 >
b11111111111111111111111111110110 N
b11111111111111111111111111110110 X
b11111111111111111111111111110110 <
b11111111111111111111111111110110 M
b11111111111111111111111111110110 W
b11111111111111111111111111110110 L
b11 K
02
#5160
b100 E
b1100100 F
b1100 /
b1100 =
b10111100 B
b11111111111111111111111111110000 C
12
#5280
0U
b11000000 [
b1111110000111 T
b1111110000111 Z
0:
b1111100100011 P
b1111100100011 Y
b1100100 Q
09
0;
b1111110000111 8
b1111110000111 V
b100 ?
b100 O
b1111100100011 >
b1111100100011 N
b1111100100011 X
b1100100 <
b1100100 M
b1100100 W
b1101 0
b1101 6
b1100 G
b10111100 A
b1100100 L
b11111111111111111111111111110000 I
b100 K
02
#5400
b1111110000111 ,
b1111110000111 @
b10 E
b10111011 B
b1101 /
b1101 =
b1101 C
12
#5520
09
0:
b11 [
1R
b11111 8
b11111 V
b11111 T
b11111 Z
b11111111111111111111111111101110 P
b10001 Y
b1101 Q
b110 ?
b110 O
b11111111111111111111111111101110 >
b11111111111111111111111111101110 N
b11111111111111111111111111101110 X
b1101 <
b1101 M
b1101 W
b1111110000111 H
b1101 G
b10111011 A
b1101 I
b10 K
b11111111111111111111111111101110 0
b11111111111111111111111111101110 6
02
#5640
b11 E
b11111 F
12
#5760
b111110 [
0R
b111110 T
b111110 Z
0:
b11111 P
b11111 Y
b11111 Q
b1111000001 8
b1111000001 V
b1000 ?
b1000 O
b11111 >
b11111 N
b11111 X
b11111 <
b11111 M
b11111 W
b11111 L
b11 K
02
#5880
b100 E
b1111000001 F
b1110 /
b1110 =
b10111010 B
b11111111111111111111111111101110 C
12
#6000
b11111100001110 [
b10001101001000 T
b10001101001000 Z
b1111110000111 P
b1111110000111 Y
b1111000001 Q
b10001101001000 8
b10001101001000 V
b100 ?
b100 O
b1111110000111 >
b1111110000111 N
b1111110000111 X
b1111000001 <
b1111000001 M
b1111000001 W
b1110 G
b10111010 A
b1111000001 L
b11111111111111111111111111101110 I
b100 K
b11111111111111111111111111111101 0
b11111111111111111111111111111101 6
02
#6120
b10001101001000 ,
b10001101001000 @
b10 E
b10111001 B
b1111 /
b1111 =
b11111111111111111111111111111101 C
12
#6240
1;
1U
0:
b111111111111111111111111111111111 [
1R
b1001 8
b1001 V
b1001 T
b1001 Z
b11111111111111111111111111110100 P
b1011 Y
b11111111111111111111111111111101 Q
09
b110 ?
b110 O
b11111111111111111111111111110100 >
b11111111111111111111111111110100 N
b11111111111111111111111111110100 X
b11111111111111111111111111111101 <
b11111111111111111111111111111101 M
b11111111111111111111111111111101 W
b11111111111111111111111111110100 0
b11111111111111111111111111110100 6
b10001101001000 H
b1111 G
b10111001 A
b11111111111111111111111111111101 I
b10 K
02
#6360
b11 E
b1001 F
12
#6480
0U
b10010 [
0R
b10010 T
b10010 Z
b1001 P
b1001 Y
b1001 Q
0;
b1010001 8
b1010001 V
b1000 ?
b1000 O
b1001 >
b1001 N
b1001 X
b1001 <
b1001 M
b1001 W
b1001 L
b11 K
02
#6600
b100 E
b1010001 F
b10000 /
b10000 =
b10111000 B
b11111111111111111111111111110100 C
12
#6720
b10000000 [
b10001110011001 T
b10001110011001 Z
b10001101001000 P
b10001101001000 Y
b1010001 Q
b10001110011001 8
b10001110011001 V
b100 ?
b100 O
b10001101001000 >
b10001101001000 N
b10001101001000 X
b1010001 <
b1010001 M
b1010001 W
b101111 0
b101111 6
b10000 G
b10111000 A
b1010001 L
b11111111111111111111111111110100 I
b100 K
02
#6840
b10001110011001 ,
b10001110011001 @
b10 E
b10110111 B
b10001 /
b10001 =
b101111 C
12
#6960
1;
1U
0:
b111111111111111111111111111111111 [
1R
b1110 8
b1110 V
b1110 T
b1110 Z
b100001 P
b11111111111111111111111111011110 Y
b101111 Q
b110 ?
b110 O
b100001 >
b100001 N
b100001 X
b101111 <
b101111 M
b101111 W
b10001110011001 H
b10001 G
b10110111 A
b101111 I
b10 K
b100001 0
b100001 6
02
#7080
b11 E
b1110 F
12
#7200
0U
b11100 [
0R
b11100 T
b11100 Z
b1110 P
b1110 Y
b1110 Q
0;
b11000100 8
b11000100 V
b1000 ?
b1000 O
b1110 >
b1110 N
b1110 X
b1110 <
b1110 M
b1110 W
b1110 L
b11 K
02
#7320
b100 E
b11000100 F
b10010 /
b10010 =
b10110110 B
b100001 C
12
#7440
b11100000000 [
b10010001011101 T
b10010001011101 Z
b10001110011001 P
b10001110011001 Y
b11000100 Q
b10010001011101 8
b10010001011101 V
b100 ?
b100 O
b10001110011001 >
b10001110011001 N
b10001110011001 X
b11000100 <
b11000100 M
b11000100 W
b10010 G
b10110110 A
b11000100 L
b100001 I
b100 K
b100010 0
b100010 6
02
#7560
b10010001011101 ,
b10010001011101 @
b10 E
b10110101 B
b10011 /
b10011 =
b100010 C
12
#7680
1;
1U
0:
b111111111111111111111111111111111 [
1R
b100010 8
b100010 V
b100010 T
b100010 Z
b0 P
b11111111111111111111111111111111 Y
b100010 Q
b110 ?
b110 O
b0 >
b0 N
b0 X
b100010 <
b100010 M
b100010 W
b0 0
b0 6
b10010001011101 H
b10011 G
b10110101 A
b100010 I
b10 K
02
#7800
b11 E
b100010 F
12
#7920
0U
b1000100 [
b1000100 T
b1000100 Z
0R
07
b100010 P
b100010 Y
0;
b10010000100 8
b10010000100 V
b1000 ?
b1000 O
b100010 >
b100010 N
b100010 X
b100010 L
b11 K
02
#8040
b100 E
b10010000100 F
b10100 /
b10100 =
b10110100 B
b0 C
12
#8160
b100000111000 [
b10100011100001 T
b10100011100001 Z
b10010001011101 P
b10010001011101 Y
b10010000100 Q
b10100011100001 8
b10100011100001 V
b100 ?
b100 O
b10010001011101 >
b10010001011101 N
b10010001011101 X
b10010000100 <
b10010000100 M
b10010000100 W
b10101 0
b10101 6
b10100 G
b10110100 A
b10010000100 L
b0 I
b100 K
02
#8280
b10100011100001 ,
b10100011100001 @
b10 E
b10110011 B
b10101 /
b10101 =
b10101 C
12
#8400
09
0:
b1011 [
1R
b111011 8
b111011 V
b111011 T
b111011 Z
b11111111111111111111111111011010 P
b100101 Y
b10101 Q
b110 ?
b110 O
b11111111111111111111111111011010 >
b11111111111111111111111111011010 N
b11111111111111111111111111011010 X
b10101 <
b10101 M
b10101 W
b10100011100001 H
b10101 G
b10110011 A
b10101 I
b10 K
b11111111111111111111111111011010 0
b11111111111111111111111111011010 6
02
#8520
b11 E
b111011 F
12
#8640
b1110110 [
0R
b1110110 T
b1110110 Z
0:
b111011 P
b111011 Y
b111011 Q
b110110011001 8
b110110011001 V
b1000 ?
b1000 O
b111011 >
b111011 N
b111011 X
b111011 <
b111011 M
b111011 W
b111011 L
b11 K
02
#8760
b100 E
b110110011001 F
b10110 /
b10110 =
b10110010 B
b11111111111111111111111111011010 C
12
#8880
b1001100000010 [
b11011001111010 T
b11011001111010 Z
b10100011100001 P
b10100011100001 Y
b110110011001 Q
b11011001111010 8
b11011001111010 V
b100 ?
b100 O
b10100011100001 >
b10100011100001 N
b10100011100001 X
b110110011001 <
b110110011001 M
b110110011001 W
b10110 G
b10110010 A
b110110011001 L
b11111111111111111111111111011010 I
b100 K
b1110 0
b1110 6
02
#9000
b11011001111010 ,
b11011001111010 @
b10 E
b10110001 B
b10111 /
b10111 =
b1110 C
12
#9120
1:
b11111 [
1R
b11111111111111111111111111011110 8
b11111111111111111111111111011110 V
b11111111111111111111111111011110 T
b11111111111111111111111111011110 Z
b110000 P
b11111111111111111111111111001111 Y
b1110 Q
b110 ?
b110 O
b110000 >
b110000 N
b110000 X
b1110 <
b1110 M
b1110 W
b110000 0
b110000 6
b11011001111010 H
b10111 G
b10110001 A
b1110 I
b10 K
02
#9240
b11 E
b11111111111111111111111111011110 F
12
#9360
1U
b111111111111111111111111110111100 [
0R
b11111111111111111111111110111100 T
b11111111111111111111111110111100 Z
0:
b11111111111111111111111111011110 P
b11111111111111111111111111011110 Y
b11111111111111111111111111011110 Q
b10010000100 8
b10010000100 V
b1000 ?
b1000 O
b11111111111111111111111111011110 >
b11111111111111111111111111011110 N
b11111111111111111111111111011110 X
b11111111111111111111111111011110 <
b11111111111111111111111111011110 M
b11111111111111111111111111011110 W
b11111111111111111111111111011110 L
b11 K
02
#9480
b100 E
b10010000100 F
b11000 /
b11000 =
b10110000 B
b110000 C
12
#9600
0U
b100000000000 [
b11101011111110 T
b11101011111110 Z
0:
b11011001111010 P
b11011001111010 Y
b10010000100 Q
09
0;
b11101011111110 8
b11101011111110 V
b100 ?
b100 O
b11011001111010 >
b11011001111010 N
b11011001111010 X
b10010000100 <
b10010000100 M
b10010000100 W
b11111111111111111111111111111101 0
b11111111111111111111111111111101 6
b11000 G
b10110000 A
b10010000100 L
b110000 I
b100 K
02
#9720
b11101011111110 ,
b11101011111110 @
b10 E
b10101111 B
b11001 /
b11001 =
b11111111111111111111111111111101 C
12
